{
  "$schema": "https://developer.microsoft.com/json-schemas/fabric/item/report/definition/visualContainer/2.8.0/schema.json",
  "name": "dfdd65fe1c3fe578bc95",
  "position": {
    "x": 16.545240893066982,
    "y": 243.66627497062282,
    "z": 10000,
    "height": 561.03407755581668,
    "width": 436.19271445358407,
    "tabOrder": 10000
  },
  "visual": {
    "visualType": "pivotTable",
    "query": {
      "queryState": {
        "Rows": {
          "projections": [
            {
              "field": {
                "Column": {
                  "Expression": {
                    "SourceRef": {
                      "Entity": "f_simulation_output_summary_executive_summary"
                    }
                  },
                  "Property": "metric"
                }
              },
              "queryRef": "f_simulation_output_summary_executive_summary.metric",
              "nativeQueryRef": "Metric",
              "active": true,
              "displayName": "Metric"
            },
            {
              "field": {
                "Column": {
                  "Expression": {
                    "SourceRef": {
                      "Entity": "f_simulation_output_summary_executive_summary"
                    }
                  },
                  "Property": "unit"
                }
              },
              "queryRef": "f_simulation_output_summary_executive_summary.unit",
              "nativeQueryRef": "Unit",
              "active": true,
              "displayName": "Unit"
            }
          ]
        },
        "Values": {
          "projections": [
            {
              "field": {
                "Measure": {
                  "Expression": {
                    "SourceRef": {
                      "Entity": "A_Measurement"
                    }
                  },
                  "Property": "Metric_Value_Format"
                }
              },
              "queryRef": "A_Measurement.Metric_Value_Format",
              "nativeQueryRef": "Value",
              "displayName": "Value"
            }
          ]
        }
      }
    },
    "expansionStates": [
      {
        "roles": [
          "Rows"
        ],
        "levels": [
          {
            "queryRefs": [
              "f_simulation_output_summary_executive_summary.metric"
            ],
            "isPinned": true
          },
          {
            "queryRefs": [
              "f_simulation_output_summary_executive_summary.unit"
            ],
            "isCollapsed": true,
            "isPinned": true
          }
        ],
        "root": {}
      }
    ],
    "objects": {
      "columnWidth": [
        {
          "properties": {
            "value": {
              "expr": {
                "Literal": {
                  "Value": "104D"
                }
              }
            }
          },
          "selector": {
            "metadata": "Sum(d_abs_main.notional)"
          }
        },
        {
          "properties": {
            "value": {
              "expr": {
                "Literal": {
                  "Value": "18D"
                }
              }
            }
          },
          "selector": {
            "data": [
              {
                "scopeId": {
                  "Comparison": {
                    "ComparisonKind": 0,
                    "Left": {
                      "Column": {
                        "Expression": {
                          "SourceRef": {
                            "Entity": "temp_MetricTable"
                          }
                        },
                        "Property": "Unit"
                      }
                    },
                    "Right": {
                      "Literal": {
                        "Value": "'#'"
                      }
                    }
                  }
                }
              }
            ]
          }
        },
        {
          "properties": {
            "value": {
              "expr": {
                "Literal": {
                  "Value": "34D"
                }
              }
            }
          },
          "selector": {
            "data": [
              {
                "scopeId": {
                  "Comparison": {
                    "ComparisonKind": 0,
                    "Left": {
                      "Column": {
                        "Expression": {
                          "SourceRef": {
                            "Entity": "temp_MetricTable"
                          }
                        },
                        "Property": "Unit"
                      }
                    },
                    "Right": {
                      "Literal": {
                        "Value": "'IDR'"
                      }
                    }
                  }
                }
              }
            ]
          }
        },
        {
          "properties": {
            "value": {
              "expr": {
                "Literal": {
                  "Value": "18D"
                }
              }
            }
          },
          "selector": {
            "data": [
              {
                "scopeId": {
                  "Comparison": {
                    "ComparisonKind": 0,
                    "Left": {
                      "Column": {
                        "Expression": {
                          "SourceRef": {
                            "Entity": "temp_MetricTable"
                          }
                        },
                        "Property": "Unit"
                      }
                    },
                    "Right": {
                      "Literal": {
                        "Value": "'x'"
                      }
                    }
                  }
                }
              }
            ]
          }
        },
        {
          "properties": {
            "value": {
              "expr": {
                "Literal": {
                  "Value": "44D"
                }
              }
            }
          },
          "selector": {
            "data": [
              {
                "scopeId": {
                  "Comparison": {
                    "ComparisonKind": 0,
                    "Left": {
                      "Column": {
                        "Expression": {
                          "SourceRef": {
                            "Entity": "temp_MetricTable"
                          }
                        },
                        "Property": "Unit"
                      }
                    },
                    "Right": {
                      "Literal": {
                        "Value": "'years'"
                      }
                    }
                  }
                }
              }
            ]
          }
        },
        {
          "properties": {
            "value": {
              "expr": {
                "Literal": {
                  "Value": "184D"
                }
              }
            }
          },
          "selector": {
            "metadata": "f_simulation_output_summary_executive_summary.metric"
          }
        },
        {
          "properties": {
            "value": {
              "expr": {
                "Literal": {
                  "Value": "44D"
                }
              }
            }
          },
          "selector": {
            "metadata": "f_simulation_output_summary_executive_summary.unit"
          }
        },
        {
          "properties": {
            "value": {
              "expr": {
                "Literal": {
                  "Value": "100.07630320564039D"
                }
              }
            }
          },
          "selector": {
            "metadata": "A_Measurement.Metric_Value_Format"
          }
        }
      ],
      "rowHeaders": [
        {
          "properties": {
            "showExpandCollapseButtons": {
              "expr": {
                "Literal": {
                  "Value": "false"
                }
              }
            },
            "outlineWeight": {
              "expr": {
                "Literal": {
                  "Value": "1D"
                }
              }
            }
          }
        }
      ],
      "values": [
        {
          "properties": {
            "bandedRowHeaders": {
              "expr": {
                "Literal": {
                  "Value": "true"
                }
              }
            },
            "fontColorPrimary": {
              "solid": {
                "color": {
                  "expr": {
                    "ThemeDataColor": {
                      "ColorId": 0,
                      "Percent": 0
                    }
                  }
                }
              }
            },
            "fontColorSecondary": {
              "solid": {
                "color": {
                  "expr": {
                    "ThemeDataColor": {
                      "ColorId": 0,
                      "Percent": 0
                    }
                  }
                }
              }
            },
            "backColorSecondary": {
              "solid": {
                "color": {
                  "expr": {
                    "Literal": {
                      "Value": "'#0A2B43'"
                    }
                  }
                }
              }
            },
            "outlineWeight": {
              "expr": {
                "Literal": {
                  "Value": "1D"
                }
              }
            }
          }
        }
      ],
      "general": [
        {
          "properties": {
            "layout": {
              "expr": {
                "Literal": {
                  "Value": "'Tabular'"
                }
              }
            }
          }
        }
      ],
      "subTotals": [
        {
          "properties": {
            "rowSubtotals": {
              "expr": {
                "Literal": {
                  "Value": "false"
                }
              }
            }
          }
        }
      ],
      "grid": [
        {
          "properties": {
            "gridHorizontal": {
              "expr": {
                "Literal": {
                  "Value": "false"
                }
              }
            },
            "outlineStyle": {
              "expr": {
                "Literal": {
                  "Value": "5D"
                }
              }
            }
          }
        }
      ],
      "columnHeaders": [
        {
          "properties": {
            "bold": {
              "expr": {
                "Literal": {
                  "Value": "true"
                }
              }
            },
            "outlineWeight": {
              "expr": {
                "Literal": {
                  "Value": "1D"
                }
              }
            }
          }
        }
      ],
      "columnFormatting": [
        {
          "properties": {
            "styleHeader": {
              "expr": {
                "Literal": {
                  "Value": "true"
                }
              }
            },
            "alignment": {
              "expr": {
                "Literal": {
                  "Value": "'Right'"
                }
              }
            }
          },
          "selector": {
            "metadata": "A_Measurement.Metric_Value_Format"
          }
        }
      ]
    },
    "visualContainerObjects": {
      "stylePreset": [
        {
          "properties": {
            "name": {
              "expr": {
                "Literal": {
                  "Value": "'Default'"
                }
              }
            }
          }
        }
      ],
      "title": [
        {
          "properties": {
            "text": {
              "expr": {
                "Literal": {
                  "Value": "'Simulation Summary Metrics'"
                }
              }
            }
          }
        }
      ]
    },
    "drillFilterOtherVisuals": true
  }
}