{
  "$schema": "https://developer.microsoft.com/json-schemas/fabric/item/report/definition/visualContainer/2.8.0/schema.json",
  "name": "bbefba2b738ae4ef2716",
  "position": {
    "x": 16,
    "y": 798,
    "z": 3000,
    "height": 360,
    "width": 616,
    "tabOrder": 3000
  },
  "visual": {
    "visualType": "areaChart",
    "query": {
      "queryState": {
        "Category": {
          "projections": [
            {
              "field": {
                "Column": {
                  "Expression": {
                    "SourceRef": {
                      "Entity": "d_dates"
                    }
                  },
                  "Property": "dashboard_month"
                }
              },
              "queryRef": "d_dates.dashboard_date",
              "nativeQueryRef": "Date",
              "active": true,
              "displayName": "Date"
            }
          ]
        },
        "Y": {
          "projections": [
            {
              "field": {
                "Aggregation": {
                  "Expression": {
                    "Column": {
                      "Expression": {
                        "SourceRef": {
                          "Entity": "f_simulation_output_metric_portfolio_performance"
                        }
                      },
                      "Property": "performing_balance"
                    }
                  },
                  "Function": 0
                }
              },
              "queryRef": "Sum(f_simulation_output_metric_portfolio_performance.performing_balance)",
              "nativeQueryRef": "Performing Balance",
              "displayName": "Performing Balance"
            }
          ]
        }
      },
      "sortDefinition": {
        "sort": [
          {
            "field": {
              "Column": {
                "Expression": {
                  "SourceRef": {
                    "Entity": "d_dates"
                  }
                },
                "Property": "dashboard_month"
              }
            },
            "direction": "Ascending"
          }
        ]
      }
    },
    "objects": {
      "legend": [
        {
          "properties": {
            "position": {
              "expr": {
                "Literal": {
                  "Value": "'TopCenter'"
                }
              }
            }
          }
        }
      ],
      "dataPoint": [
        {
          "properties": {
            "fill": {
              "solid": {
                "color": {
                  "expr": {
                    "Literal": {
                      "Value": "'#457B9D'"
                    }
                  }
                }
              }
            },
            "transparency": {
              "expr": {
                "Literal": {
                  "Value": "0D"
                }
              }
            }
          },
          "selector": {
            "metadata": "Sum(f_simulation_output_metric_portfolio_performance.performing_balance)"
          }
        }
      ],
      "lineStyles": [
        {
          "properties": {
            "strokeShow": {
              "expr": {
                "Literal": {
                  "Value": "false"
                }
              }
            },
            "lineChartType": {
              "expr": {
                "Literal": {
                  "Value": "'smooth'"
                }
              }
            }
          },
          "selector": {
            "metadata": "Sum(f_simulation_output_metric_portfolio_performance.performing_balance)"
          }
        }
      ]
    },
    "visualContainerObjects": {
      "title": [
        {
          "properties": {
            "show": {
              "expr": {
                "Literal": {
                  "Value": "true"
                }
              }
            },
            "titleWrap": {
              "expr": {
                "Literal": {
                  "Value": "true"
                }
              }
            },
            "fontSize": {
              "expr": {
                "Literal": {
                  "Value": "'12'"
                }
              }
            },
            "bold": {
              "expr": {
                "Literal": {
                  "Value": "true"
                }
              }
            },
            "text": {
              "expr": {
                "Literal": {
                  "Value": "'Performing Balance Trend'"
                }
              }
            }
          }
        }
      ],
      "subTitle": [
        {
          "properties": {
            "show": {
              "expr": {
                "Literal": {
                  "Value": "false"
                }
              }
            },
            "fontSize": {
              "expr": {
                "Literal": {
                  "Value": "'11'"
                }
              }
            }
          }
        }
      ],
      "divider": [
        {
          "properties": {
            "show": {
              "expr": {
                "Literal": {
                  "Value": "false"
                }
              }
            },
            "width": {
              "expr": {
                "Literal": {
                  "Value": "1D"
                }
              }
            }
          }
        }
      ],
      "spacing": [
        {
          "properties": {
            "customizeSpacing": {
              "expr": {
                "Literal": {
                  "Value": "true"
                }
              }
            },
            "spaceBelowTitle": {
              "expr": {
                "Literal": {
                  "Value": "10D"
                }
              }
            }
          }
        }
      ],
      "background": [
        {
          "properties": {
            "show": {
              "expr": {
                "Literal": {
                  "Value": "true"
                }
              }
            },
            "color": {
              "solid": {
                "color": {
                  "expr": {
                    "Literal": {
                      "Value": "'#0A2B43'"
                    }
                  }
                }
              }
            },
            "transparency": {
              "expr": {
                "Literal": {
                  "Value": "0D"
                }
              }
            }
          }
        }
      ],
      "padding": [
        {
          "properties": {
            "top": {
              "expr": {
                "Literal": {
                  "Value": "15D"
                }
              }
            },
            "bottom": {
              "expr": {
                "Literal": {
                  "Value": "15D"
                }
              }
            },
            "left": {
              "expr": {
                "Literal": {
                  "Value": "15D"
                }
              }
            },
            "right": {
              "expr": {
                "Literal": {
                  "Value": "15D"
                }
              }
            }
          }
        }
      ],
      "border": [
        {
          "properties": {
            "show": {
              "expr": {
                "Literal": {
                  "Value": "true"
                }
              }
            },
            "color": {
              "solid": {
                "color": {
                  "expr": {
                    "Literal": {
                      "Value": "'#0A2B43'"
                    }
                  }
                }
              }
            },
            "radius": {
              "expr": {
                "Literal": {
                  "Value": "9D"
                }
              }
            },
            "width": {
              "expr": {
                "Literal": {
                  "Value": "0.5D"
                }
              }
            }
          }
        }
      ],
      "dropShadow": [
        {
          "properties": {
            "show": {
              "expr": {
                "Literal": {
                  "Value": "false"
                }
              }
            },
            "preset": {
              "expr": {
                "Literal": {
                  "Value": "'Custom'"
                }
              }
            },
            "position": {
              "expr": {
                "Literal": {
                  "Value": "'Outer'"
                }
              }
            },
            "color": {
              "solid": {
                "color": {
                  "expr": {
                    "Literal": {
                      "Value": "'#0B1215'"
                    }
                  }
                }
              }
            },
            "transparency": {
              "expr": {
                "Literal": {
                  "Value": "65D"
                }
              }
            },
            "shadowSpread": {
              "expr": {
                "Literal": {
                  "Value": "2D"
                }
              }
            },
            "shadowBlur": {
              "expr": {
                "Literal": {
                  "Value": "12D"
                }
              }
            },
            "angle": {
              "expr": {
                "Literal": {
                  "Value": "90D"
                }
              }
            },
            "shadowDistance": {
              "expr": {
                "Literal": {
                  "Value": "4D"
                }
              }
            }
          }
        }
      ],
      "stylePreset": [
        {
          "properties": {
            "name": {
              "expr": {
                "Literal": {
                  "Value": "'Default'"
                }
              }
            }
          }
        }
      ]
    },
    "drillFilterOtherVisuals": true
  },
  "filterConfig": {
    "filters": [
      {
        "name": "0fda8eceba155e73ef03",
        "field": {
          "Column": {
            "Expression": {
              "SourceRef": {
                "Entity": "d_dates"
              }
            },
            "Property": "endofmonth"
          }
        },
        "type": "Advanced",
        "howCreated": "User"
      }
    ]
  }
}